{
  "chainName": "IRISnet",
  "chainId": "irishub-1",
  "displayHubName": "IRISnet",
  "rpc": "https://iris-public-rpc.stafihub.io",
  "restEndpoint": "https://iris-public-rpc.stafihub.io",
  "denom": "uiris",
  "coinDenom": "IRIS",
  "decimals": 6,
  "bech32Config": {
    "bech32PrefixAccAddr": "iaa",
    "bech32PrefixAccPub": "iap",
    "bech32PrefixValAddr": "iva",
    "bech32PrefixValPub": "ivp",
    "bech32PrefixConsAddr": "ica",
    "bech32PrefixConsPub": "icp"
  },
  "explorerUrl": "https://ping.pub/iris-network",
  "defaultApy": "10",
  "sortIndex": 2,
  "isNativeKeplrChain": true,
  "stakeDisabled": true
}
